{
  "$schema": "https://ui.shadcn.com/schema/registry-item.json",
  "name": "search-field",
  "type": "registry:ui",
  "title": "SearchField",
  "description": "SearchField component",
  "dependencies": ["react-aria-components", "lucide-react"],
  "registryDependencies": ["@twc-ui/button", "@twc-ui/field", "@twc-ui/text-field"],
  "files": [
    {
      "path": "resources/js/components/twc-ui/search-field.tsx",
      "type": "registry:ui",
      "target": "components/twc-ui/search-field.tsx"
    }
  ]
}
